superplot/__init__.py
superplot/alt_config.yml
superplot/config.yml
superplot/create_home_dir.py
superplot/data_loader.py
superplot/plot_options.py
superplot/schemes.py
superplot/summary.py
superplot/super_command.py
superplot/super_gui.py
superplot/example/SB_MO_log_all.info
superplot/example/SB_MO_log_allpost.txt
superplot/example/__init__.py
superplot/example/gaussian_.txt
superplot/example/load_pkl.py
superplot/example/merge_pkl.py
superplot/example/two_plots.py
superplot/plotlib/__init__.py
superplot/plotlib/base.py
superplot/plotlib/plot_mod.py
superplot/plotlib/plots.py
superplot/plotlib/styles/OneDimChiSq.mplstyle
superplot/plotlib/styles/OneDimStandard.mplstyle
superplot/plotlib/styles/Scatter.mplstyle
superplot/plotlib/styles/TwoDimPlotFilledPDF.mplstyle
superplot/plotlib/styles/TwoDimPlotFilledPL.mplstyle
superplot/plotlib/styles/TwoDimPlotPDF.mplstyle
superplot/plotlib/styles/TwoDimPlotPL.mplstyle
superplot/plotlib/styles/__init__.py
superplot/plotlib/styles/default.mplstyle
superplot/statslib/__init__.py
superplot/statslib/kde.py
superplot/statslib/one_dim.py
superplot/statslib/patched_joblib.py
superplot/statslib/point.py
superplot/statslib/two_dim.py
superplot-2.0.4.dist-info/DESCRIPTION.rst
superplot-2.0.4.dist-info/METADATA
superplot-2.0.4.dist-info/RECORD
superplot-2.0.4.dist-info/WHEEL
superplot-2.0.4.dist-info/entry_points.txt
superplot-2.0.4.dist-info/metadata.json
superplot-2.0.4.dist-info/top_level.txt
