Metadata-Version: 2.0
Name: superplot
Version: 2.0.4
Summary: Python GUI for plotting SuperPy/SuperBayes/MultiNest/BAYES-X results
Home-page: https://github.com/michaelhb/superplot
Author: Andrew Fowlie, Michael Bardsley
Author-email: mhbar3@student.monash.edu
License: GPL v2
Platform: UNKNOWN
Requires-Dist: appdirs
Requires-Dist: joblib
Requires-Dist: numpy
Requires-Dist: pandas
Requires-Dist: prettytable
Requires-Dist: scipy
Requires-Dist: simpleyaml
